{
  "king-p3nguin": 15,
  "anushkrishnav": 6,
  "AbdullahKazi500": 6,
  "Yash-10": 5,
  "WingCode": 5,
  "Gopal-Dahale": 4,
  "jyotiraj-code": 4,
  "Fe-r-oz": 4,
  "Manvi-Agrawal": 4,
  "Tarun-Kumar07": 4,
  "golanor": 3,
  "atomgardner": 3,
  "Roshan-Thomas": 3,
  "tomv42": 3,
  "cburdine": 2,
  "SaashaJoshi": 2,
  "maxwell04-wq": 2,
  "ErikQQY": 2,
  "abidart": 2,
  "atharva-satpute": 2,
  "rodolfocarobene": 2,
  "Piwakk": 2,
  "divshacker": 2,
  "ducthanh1991": 1,
  "Qubit1718": 1,
  "ejthomas": 1,
  "nirajvenkat": 1,
  "schance995": 1,
  "0mWh": 1,
  "idriss-hamadi": 1,
  "MashAliK": 1,
  "burlemarxiste": 1,
  "daredevil3435": 1,
  "shubhusion": 1,
  "qmanning4": 1,
  "marcogobbo": 1,
  "obliviateandsurrender": 1,
  "ArturDomingues": 1,
  "alan-nala": 1,
  "YangLiuWillow": 1,
  "ahkatlio": 1,
  "prakharb10": 1,
  "shravanpatel30": 1,
  "LorenzoFioroni": 1,
  "samu-sys": 1,
  "ilkclord": 1,
  "aarontrowbridge": 1,
  "dhanaabhirajk": 1,
  "tnemoz": 1,
  "EuGig": 1,
  "AVDiv": 1,
  "ljcamargo": 1,
  "jpacold": 1,
  "NnguyenHTommy": 1,
  "EmilianoG-byte": 1,
  "rmoretti9": 1,
  "PietroCampana": 1,
  "f-martini": 1,
  "abhamra": 1,
  "Barnald": 1,
  "SoshunNaito": 1
}